path_version.py
path_version-0.1.50.dist-info/WHEEL
path_version-0.1.50.dist-info/METADATA
path_version-0.1.50.dist-info/RECORD
