Metadata-Version: 2.1
Name: path-version
Version: 0.1.50
Summary: Get the last changed has of a dir as a python function
License: Proprietary
Author: Oxford Ionics
Requires-Python: >=3.8,<4.0
Classifier: License :: Other/Proprietary License
Classifier: Programming Language :: Python :: 3
Classifier: Programming Language :: Python :: 3.8
Classifier: Programming Language :: Python :: 3.9
Classifier: Programming Language :: Python :: 3.10
Classifier: Programming Language :: Python :: 3.11
